process_supervision/README.md
process_supervision/__init__.py
process_supervision/generator.py
process_supervision/main.py
process_supervision/prm.py
process_supervision_torch-0.0.3.dist-info/LICENSE
process_supervision_torch-0.0.3.dist-info/WHEEL
process_supervision_torch-0.0.3.dist-info/METADATA
process_supervision_torch-0.0.3.dist-info/RECORD
