Metadata-Version: 2.1
Name: process-supervision-torch
Version: 0.0.3
Summary: Process SuperVision - Pytorch
Home-page: https://github.com/kyegomez/Lets-Verify-Step-by-Step
License: MIT
Keywords: artificial intelligence,deep learning,optimizers,Prompt Engineering
Author: Kye Gomez
Author-email: kye@apac.ai
Requires-Python: >=3.8.1,<4.0.0
Classifier: Development Status :: 4 - Beta
Classifier: Intended Audience :: Developers
Classifier: License :: OSI Approved :: MIT License
Classifier: Programming Language :: Python :: 3
Classifier: Programming Language :: Python :: 3.9
Classifier: Programming Language :: Python :: 3.10
Classifier: Programming Language :: Python :: 3.11
Classifier: Programming Language :: Python :: 3.6
Classifier: Topic :: Scientific/Engineering :: Artificial Intelligence
Requires-Dist: autopep8
Requires-Dist: black
Requires-Dist: rich
Requires-Dist: ruff
Requires-Dist: swarms
Requires-Dist: transformers
Requires-Dist: trl
Requires-Dist: zetascale
Project-URL: Documentation, https://swarms.apac.ai
Project-URL: Repository, https://github.com/kyegomez/Lets-Verify-Step-by-Step
